[
    {
        "id": "17102025-01",
        "date": "17/10/2025",
        "entries": [
            { "entry": "Singapore", "player": "AG" },
            { "entry": "England", "player": "DJ" },
            { "entry": "Dharwad", "player": "AG" },
            { "entry": "Denmark", "player": "D" },
            { "entry": "Kolkata", "player": "AG"}
        ],
        "status": "In Progress"
    },
    {
        "id": "15102025-01",
        "date": "15/10/2025",
        "entries": [
            { "entry": "Denmark", "player": "D" },
            { "entry": "Asmara", "player": "A" },
            { "entry": "Dakar", "player": "D" },
            { "entry": "Antarctica", "player": "A" }
        ],
        "status": "Completed (Player D could not follow 'Antarctica' with a 'D' entry.)"
    },
    {
        "id": "10102025-01",
        "date": "10/10/2025",
        "entries": [
            { "entry": "Angola", "player": "A" },
            { "entry": "Delaware", "player": "D" },
            { "entry": "Alabama", "player": "A" },
            { "entry": "Doha", "player": "D" }
        ],
        "status": "Completed (Player A could not follow 'Doha' with an 'A' entry.)"
    }
]



